saullo_castro_tenure_review/__init__.py
saullo_castro_tenure_review/dataset.py
saullo_castro_tenure_review/model_database.py
saullo_castro_tenure_review/modelpyfe3d.py
saullo_castro_tenure_review/version.py
saullo_castro_tenure_review/data/__init__.py
saullo_castro_tenure_review/data/pCRM9_wing/README.md
saullo_castro_tenure_review/data/pCRM9_wing/__init__.py
saullo_castro_tenure_review/data/pCRM9_wing/pCRM9_103_MAIN_FILE.bdf
saullo_castro_tenure_review/data/pCRM9_wing/pCRM9_CONM2_MTOW.dat
saullo_castro_tenure_review/data/pCRM9_wing/pCRM9_PSHELL.dat
saullo_castro_tenure_review/data/pCRM9_wing/pCRM9_mat.dat
saullo_castro_tenure_review/data/pCRM9_wing/pCRM9_model_2.dat
saullo_castro_tenure_review/data/pCRM9_wing/pCRM9_ribs_fem.dat
saullo_castro_tenure_review-1.0.0.data/data/AUTHORS
saullo_castro_tenure_review-1.0.0.data/data/LICENSE
saullo_castro_tenure_review-1.0.0.data/data/README.md
saullo_castro_tenure_review-1.0.0.dist-info/AUTHORS
saullo_castro_tenure_review-1.0.0.dist-info/LICENSE
saullo_castro_tenure_review-1.0.0.dist-info/METADATA
saullo_castro_tenure_review-1.0.0.dist-info/WHEEL
saullo_castro_tenure_review-1.0.0.dist-info/top_level.txt
saullo_castro_tenure_review-1.0.0.dist-info/RECORD
